devos/__init__.py
devos/enricher.py
devos/fetcher.py
devos/gister.py
devos/prefixes.py
devos/util.py
devos_py-1.0.1.dist-info/LICENSE
devos_py-1.0.1.dist-info/METADATA
devos_py-1.0.1.dist-info/WHEEL
devos_py-1.0.1.dist-info/top_level.txt
devos_py-1.0.1.dist-info/RECORD
