Metadata-Version: 2.1
Name: devos-py
Version: 1.0.1
Summary: A tool to Depict Vocabulary Summaries
Author: Jhon Toledo, Oscar Corcho, María Poveda Villalón
Author-email: Ahmad Alobaid <aalobaid@fi.upm.es>
License: Apache License
Project-URL: Homepage, https://github.com/oeg-upm/Devos
Keywords: ontology summary,ontology diagrams,ontology documentation
Classifier: Programming Language :: Python
Classifier: Programming Language :: Python :: 3
Classifier: License :: OSI Approved :: Apache Software License
Requires-Python: >=3.0
License-File: LICENSE
Requires-Dist: Flask (==2.2.2)
Requires-Dist: nltk (==3.7)
Requires-Dist: rdflib (==6.2.0)
Requires-Dist: requests (==2.28.2)
Requires-Dist: scikit-learn (==1.2.0)
Requires-Dist: seaborn (==0.12.1)
Requires-Dist: tomli ; python_version > "3.0"
Provides-Extra: dev
Requires-Dist: codecov ; extra == 'dev'
